Elasticsearch_to_BigQuery_Connector/__init__.py
Elasticsearch_to_BigQuery_Connector/main.py
Elasticsearch_to_BigQuery_Connector-0.1.dist-info/METADATA
Elasticsearch_to_BigQuery_Connector-0.1.dist-info/WHEEL
Elasticsearch_to_BigQuery_Connector-0.1.dist-info/entry_points.txt
Elasticsearch_to_BigQuery_Connector-0.1.dist-info/top_level.txt
Elasticsearch_to_BigQuery_Connector-0.1.dist-info/RECORD
