Metadata-Version: 2.1
Name: Elasticsearch-to-BigQuery-Connector
Version: 0.1
Requires-Dist: elasticsearch
Requires-Dist: google-cloud-bigquery
